py_shr_parser-1.0.0.dist-info/licenses/LICENSE
shr_parser/__init__.py
shr_parser/enumerations.py
shr_parser/exceptions.py
shr_parser/metadata.py
shr_parser/shr_parser.py
shr_parser/version.py
shr_parser/visualization/__init__.py
shr_parser/visualization/spectrogram.py
shr_parser/visualization/spectrum.py
shr_parser/visualization/units.py
py_shr_parser-1.0.0.dist-info/METADATA
py_shr_parser-1.0.0.dist-info/WHEEL
py_shr_parser-1.0.0.dist-info/top_level.txt
py_shr_parser-1.0.0.dist-info/RECORD
