Metadata-Version: 2.4
Name: py-shr-parser
Version: 1.0.0
Summary: Python library for parsing Signal Hound SHR files
Author-email: Tom Schmitz <tschmitz@andrew.cmu.edu>
License-Expression: BSD-3-Clause
Project-URL: Homepage, https://github.com/WiseLabCMU/py-shr-parser
Project-URL: Bug Tracker, https://github.com/WiseLabCMU/py-shr-parser/issues
Keywords: SHR,Signal Hound
Classifier: Development Status :: 5 - Production/Stable
Classifier: Programming Language :: Python :: 3
Classifier: Operating System :: OS Independent
Requires-Python: >=3.8
License-File: LICENSE
Requires-Dist: numpy
Requires-Dist: matplotlib
Dynamic: license-file
